odoo/addons/report_pdf_zip_download/README.rst
odoo/addons/report_pdf_zip_download/__init__.py
odoo/addons/report_pdf_zip_download/__manifest__.py
odoo/addons/report_pdf_zip_download/controllers/__init__.py
odoo/addons/report_pdf_zip_download/controllers/main.py
odoo/addons/report_pdf_zip_download/i18n/report_pdf_zip_download.pot
odoo/addons/report_pdf_zip_download/models/__init__.py
odoo/addons/report_pdf_zip_download/models/ir_actions_report.py
odoo/addons/report_pdf_zip_download/readme/CONFIGURE.rst
odoo/addons/report_pdf_zip_download/readme/CONTRIBUTORS.rst
odoo/addons/report_pdf_zip_download/readme/DESCRIPTION.rst
odoo/addons/report_pdf_zip_download/static/description/icon.png
odoo/addons/report_pdf_zip_download/static/description/index.html
odoo/addons/report_pdf_zip_download/static/src/js/action_manager_report.js
odoo/addons/report_pdf_zip_download/views/ir_actions_report_views.xml
odoo/addons/report_pdf_zip_download/views/web_client_templates.xml
odoo12_addon_report_pdf_zip_download-12.0.1.0.0.99.dev2.dist-info/METADATA
odoo12_addon_report_pdf_zip_download-12.0.1.0.0.99.dev2.dist-info/WHEEL
odoo12_addon_report_pdf_zip_download-12.0.1.0.0.99.dev2.dist-info/top_level.txt
odoo12_addon_report_pdf_zip_download-12.0.1.0.0.99.dev2.dist-info/RECORD
